apt/__init__.py
apt/anonymization/__init__.py
apt/anonymization/anonymizer.py
apt/minimization/__init__.py
apt/minimization/minimizer.py
apt/risk/__init__.py
apt/risk/data_assessment/__init__.py
apt/risk/data_assessment/attack_strategy_utils.py
apt/risk/data_assessment/dataset_assessment_manager.py
apt/risk/data_assessment/dataset_attack.py
apt/risk/data_assessment/dataset_attack_membership_classification.py
apt/risk/data_assessment/dataset_attack_membership_knn_probabilities.py
apt/risk/data_assessment/dataset_attack_result.py
apt/risk/data_assessment/dataset_attack_whole_dataset_knn_distance.py
apt/utils/__init__.py
apt/utils/dataset_utils.py
apt/utils/datasets/__init__.py
apt/utils/datasets/datasets.py
apt/utils/models/__init__.py
apt/utils/models/keras_model.py
apt/utils/models/model.py
apt/utils/models/pytorch_model.py
apt/utils/models/sklearn_model.py
apt/utils/models/xgboost_model.py
ai_privacy_toolkit-0.2.1.dist-info/LICENSE
ai_privacy_toolkit-0.2.1.dist-info/METADATA
ai_privacy_toolkit-0.2.1.dist-info/WHEEL
ai_privacy_toolkit-0.2.1.dist-info/top_level.txt
ai_privacy_toolkit-0.2.1.dist-info/RECORD
