Metadata-Version: 2.1
Name: ai-privacy-toolkit
Version: 0.2.1
Summary: A toolkit for tools and techniques related to the privacy and compliance of AI models.
Home-page: https://github.com/IBM/ai-privacy-toolkit
Author: Abigail Goldsteen
Author-email: abigailt@il.ibm.com
Project-URL: Documentation, https://ai-privacy-toolkit.readthedocs.io/en/latest/
Classifier: Programming Language :: Python :: 3
Classifier: License :: OSI Approved :: MIT License
Classifier: Operating System :: OS Independent
Requires-Python: >=3.6
License-File: LICENSE
